EngineeringToolbox/__init__.py
EngineeringToolbox/EngineeringMechanics/__init__.py
EngineeringToolbox/EngineeringMechanics/mcnx.py
EngineeringToolbox/EngineeringMechanics/statics.py
EngineeringToolbox/Materials/__init__.py
EngineeringToolbox/Materials/materialTesting.py
EngineeringToolbox/Miscellaneous/__init__.py
EngineeringToolbox/Miscellaneous/circuitbuilder.py
EngineeringToolbox/Miscellaneous/deltadesigntool.py
EngineeringToolbox/Thermodynamics/__init__.py
EngineeringToolbox/Thermodynamics/catt.py
EngineeringToolbox/materials/__init__.py
EngineeringToolbox/materials/materialTesting.py
EngineeringToolbox/mechanics/__init__.py
EngineeringToolbox/mechanics/mcnx.py
EngineeringToolbox/mechanics/statics.py
EngineeringToolbox/miscellaneous/__init__.py
EngineeringToolbox/miscellaneous/circuitbuilder.py
EngineeringToolbox/miscellaneous/deltadesigntool.py
EngineeringToolbox/thermodynamics/__init__.py
EngineeringToolbox/thermodynamics/catt.py
EngineeringToolbox_JP-0.0.2.dist-info/LICENSE
EngineeringToolbox_JP-0.0.2.dist-info/METADATA
EngineeringToolbox_JP-0.0.2.dist-info/WHEEL
EngineeringToolbox_JP-0.0.2.dist-info/top_level.txt
EngineeringToolbox_JP-0.0.2.dist-info/RECORD
