Metadata-Version: 2.1
Name: EngineeringToolbox-JP
Version: 0.0.2
Summary: Package containing python programs for common problems in mechanical engineering curriculum.
Home-page: https://github.com/jhphillips1029/EngineeringToolbox
Author: Joshua H. Phillips
License: UNKNOWN
Platform: UNKNOWN
Classifier: Programming Language :: Python :: 3
Classifier: License :: OSI Approved :: MIT License
Classifier: Operating System :: OS Independent
Requires-Python: >=3.6
